{"chunk_definitions":[{"row":89,"row_count":1,"visible":true,"expansion_state":0,"options":{"engine":"r","echo":false,"label":"unnamed-chunk-9","dev":"png"},"document_id":"9D535FC7","chunk_id":"cyzvvgkg3g4hh","chunk_label":"unnamed-chunk-1"},{"row":114,"row_count":1,"visible":true,"expansion_state":0,"options":{"engine":"r","echo":false,"label":"unnamed-chunk-14","dev":"png"},"document_id":"9D535FC7","chunk_id":"cybj14s3ml6hy","chunk_label":"unnamed-chunk-2"},{"row":130,"row_count":1,"visible":true,"expansion_state":0,"options":{"engine":"r","echo":false,"label":"unnamed-chunk-1","dev":"png"},"document_id":"9D535FC7","chunk_id":"ckaw1st46bweq","chunk_label":"unnamed-chunk-3"}],"doc_write_time":1706156026}